adafruit_ds3231.py
adafruit_circuitpython_ds3231-2.4.24.dist-info/licenses/LICENSE
adafruit_circuitpython_ds3231-2.4.24.dist-info/METADATA
adafruit_circuitpython_ds3231-2.4.24.dist-info/WHEEL
adafruit_circuitpython_ds3231-2.4.24.dist-info/top_level.txt
adafruit_circuitpython_ds3231-2.4.24.dist-info/RECORD
